allauth_ui/__init__.py
allauth_ui/apps.py
allauth_ui/locale/es/LC_MESSAGES/django.po
allauth_ui/locale/fr/LC_MESSAGES/django.po
allauth_ui/locale/it/LC_MESSAGES/django.po
allauth_ui/locale/pt_BR/LC_MESSAGES/django.po
allauth_ui/locale/tr/LC_MESSAGES/django.po
allauth_ui/static/allauth_ui/input.css
allauth_ui/static/allauth_ui/output.css
allauth_ui/templates/account/account_inactive.html
allauth_ui/templates/account/base_reauthenticate.html
allauth_ui/templates/account/confirm_login_code.html
allauth_ui/templates/account/email.html
allauth_ui/templates/account/email_confirm.html
allauth_ui/templates/account/login.html
allauth_ui/templates/account/logout.html
allauth_ui/templates/account/password_change.html
allauth_ui/templates/account/password_reset.html
allauth_ui/templates/account/password_reset_done.html
allauth_ui/templates/account/password_reset_from_key.html
allauth_ui/templates/account/password_reset_from_key_done.html
allauth_ui/templates/account/password_set.html
allauth_ui/templates/account/reauthenticate.html
allauth_ui/templates/account/request_login_code.html
allauth_ui/templates/account/signup.html
allauth_ui/templates/account/signup_closed.html
allauth_ui/templates/account/verification_sent.html
allauth_ui/templates/allauth/layouts/base.html
allauth_ui/templates/components/container.html
allauth_ui/templates/components/form.html
allauth_ui/templates/components/form_field.html
allauth_ui/templates/mfa/authenticate.html
allauth_ui/templates/mfa/index.html
allauth_ui/templates/mfa/reauthenticate.html
allauth_ui/templates/mfa/recovery_codes/generate.html
allauth_ui/templates/mfa/recovery_codes/index.html
allauth_ui/templates/mfa/totp/activate_form.html
allauth_ui/templates/mfa/totp/deactivate_form.html
allauth_ui/templates/socialaccount/authentication_error.html
allauth_ui/templates/socialaccount/connections.html
allauth_ui/templates/socialaccount/login.html
allauth_ui/templates/socialaccount/signup.html
django_allauth_ui-1.8.1.dist-info/LICENSE
django_allauth_ui-1.8.1.dist-info/METADATA
django_allauth_ui-1.8.1.dist-info/WHEEL
django_allauth_ui-1.8.1.dist-info/RECORD
