Metadata-Version: 2.3
Name: django-allauth-ui
Version: 1.8.1
Summary: 
License: MIT
Keywords: django,allauth,social-login,auth
Author: Dani Hodovic
Author-email: you@example.com
Requires-Python: >=3.8
Classifier: Framework :: Django
Classifier: License :: OSI Approved :: MIT License
Classifier: Programming Language :: Python :: 3
Classifier: Programming Language :: Python :: 3.8
Classifier: Programming Language :: Python :: 3.9
Classifier: Programming Language :: Python :: 3.10
Classifier: Programming Language :: Python :: 3.11
Classifier: Programming Language :: Python :: 3.12
Classifier: Programming Language :: Python :: 3.13
Classifier: Topic :: Internet :: WWW/HTTP
Classifier: Topic :: System :: Systems Administration :: Authentication/Directory
Requires-Dist: django-widget-tweaks (>=1.5.0,<2.0.0)
Requires-Dist: slippers (>=0.6.2,<0.7.0)
Project-URL: Repository, https://github.com/danihodovic/django-allauth-ui
